{
  "posts": [
    {
        "id": 1,
        "title": "Boas Práticas ao Programar",
        "body": "Apesar disso, se na criação do código o programador seguir regras básicas usando as boas práticas de programação que serão mostradas nesse artigo, essa ...",
        "categoriasid": 1,
        "usersid": 1,
        "gostao": 25,
        "ngostao": 1,
        "comentario": 5
    },
    {
        "id": 2,
        "title": "Como é o dia a dia de um Programador",
        "body": "O programador é responsável por desenvolver aplicativos e softwares para diversos dispositivos eletrônicos. Conheça os cargos, o mercado de trabalho, ...",
        "categoriasid": 3,
        "usersid": 1,
        "gostao": 22,
        "ngostao": 4,
        "comentario": 12
    },
    {
        "id": 3,
        "title": "5 Caracteristicas de um bom programador",
        "body": "A profissão de programador é uma das que têm chamado mais atenção dos estudantes que ingressam nas áreas relacionadas à tecnologia ...",
        "categoriasid": 1,
        "usersid": 2,
        "gostao": 2,
        "ngostao": 10,
        "comentario": 15
    },
    {
        "id": 4,
        "title": "Vida de programador",
        "body": "Está querendo ingressar na carreira de programador e não sabe por onde começar? Então veja o que você precisa aprender primeiro...",
        "categoriasid": 2,
        "usersid": 2,
        "gostao": 35,
        "ngostao": 15,
        "comentario": 55
    }
],
"users": [
    {
        "id": 1,
        "nomecompleto": "Carlos Cavalheiro",
        "email": "ocarlosleu@gmail.com",
        "senha": "123456",
        "profissao": "Instrutor de Informática",
        "cidade": "Lençóis Paulista",
        "estado": "São Paulo"
    },
    {
        "id": 2,
        "nomecompleto": "João da Silva",
        "email": "jsilva@gmail.com",
        "senha": "123456",
        "profissao": "Web Developer",
        "cidade": "Agudos",
        "estado": "São Paulo"
    }
],
"categorias": [
    {
        "id": 1,
        "categoria": "Texto"
    },
    {
        "id": 2,
        "categoria": "Foto"
    },
    {
        "id": 3,
        "categoria": "Vídeo"
    },
    {
        "id": 4,
        "categoria": "Código"
    },
    {
        "id": 5,
        "categoria": "Link"
    }
]
}
